redis_admin/__about__.py
redis_admin/__init__.py
redis_admin/admin.py
redis_admin/client.py
redis_admin/models.py
redis_admin/settings.py
test_redis_admin/__init__.py
test_redis_admin/manage.py
test_redis_admin/settings.py
test_redis_admin/urls.py
test_redis_admin/wsgi.py
django_redis_admin-0.3.0.dist-info/METADATA
django_redis_admin-0.3.0.dist-info/WHEEL
django_redis_admin-0.3.0.dist-info/top_level.txt
django_redis_admin-0.3.0.dist-info/RECORD
