Metadata-Version: 2.1
Name: django-redis-admin
Version: 0.3.0
Summary: A Django Admin interface for Redis servers with optional Redis Sentinel support
Home-page: https://github.com/WoLpH/django-redis-admin
Author: Rick van Hattem (Wolph)
Author-email: wolph@wol.ph
License: BSD
Keywords: Django Redis Admin
Classifier: Development Status :: 5 - Production/Stable
Classifier: Environment :: Web Environment
Classifier: Intended Audience :: Developers
Classifier: License :: OSI Approved :: BSD License
Classifier: Natural Language :: English
Classifier: Programming Language :: Python :: 3.6
Classifier: Programming Language :: Python :: 3.7
Classifier: Programming Language :: Python :: 3.8
Requires-Dist: redis
Requires-Dist: django
Provides-Extra: docs
Requires-Dist: sphinx >=1.7.4 ; extra == 'docs'
Provides-Extra: tests
Requires-Dist: pytest ; extra == 'tests'
